{"notes":[{"typeOfSection":0,"lengthInSteps":16,"sectionNotes":[],"mustHitSection":true},{"typeOfSection":0,"lengthInSteps":16,"sectionNotes":[],"mustHitSection":true},{"typeOfSection":0,"lengthInSteps":16,"sectionNotes":[],"mustHitSection":false},{"typeOfSection":0,"lengthInSteps":16,"sectionNotes":[],"mustHitSection":false},{"typeOfSection":0,"lengthInSteps":16,"sectionNotes":[[11002.5,6,0,false,false,null],[11737.5,7,0,false,false,null],[11925,4,450,false,false,null],[10305,2,0,false,false,null],[10590,1,0,false,false,null],[9960,3,0,false,false,null],[10098.75,0,0,false,false,null],[9791.25,3,0],[9633.75,3,0],[10350,3,0],[10650,0,0],[11512.5,5,150],[11100,7,300]],"mustHitSection":true},{"typeOfSection":0,"lengthInSteps":16,"sectionNotes":[[12390,1,0,false,false,null],[12813.75,3,0,false,false,null],[13275,2,0,false,false,null],[13571.25,0,0,false,false,null],[14250,3,0,false,false,null],[13050,3,0],[13278.75,3,0],[13800,2,150],[14250,0,0],[12945,0,0],[12671.25,0,0]],"mustHitSection":false},{"typeOfSection":0,"lengthInSteps":16,"sectionNotes":[[15881.25,2,0,false,false,null],[16350,3,0,false,false,null],[16616.25,0,0,false,false,null],[14763.75,1,0],[15108.75,2,0],[15450,3,0],[14756.25,3,0],[15108.75,0,0],[15450,1,0],[16200,0,0]],"mustHitSection":false},{"typeOfSection":0,"lengthInSteps":16,"sectionNotes":[[16800,1,0,false,false,null],[17062.5,3,0,false,false,null],[17287.5,2,0,false,false,null],[17550,3,0,false,false,null],[17745,0,0,false,false,null],[19136.25,1,450,false,false,null],[17940,1,0],[18663.75,2,0],[18150,0,450]],"mustHitSection":false},{"typeOfSection":0,"lengthInSteps":16,"sectionNotes":[[19751.25,2,0,false,false,null],[20013.75,3,0,false,false,null],[20801.25,6,0,false,false,null],[20895,7,0],[21093.75,4,0],[21300,5,150],[21525,7,0],[20250,0,300],[20550,3,0]],"mustHitSection":false},{"typeOfSection":0,"lengthInSteps":16,"sectionNotes":[[22117.5,1,0],[22350,0,0],[22586.25,3,0],[22725,0,0],[23021.25,3,0],[23017.5,2,0],[23400,0,0],[23550,2,150],[21675,0,300]],"mustHitSection":true},{"typeOfSection":0,"lengthInSteps":16,"sectionNotes":[[24000,0,0],[24000,3,0],[24600,1,0],[24900,2,0],[25200,3,0],[25650,2,0],[25950,2,0],[26100,3,0],[24600,3,0],[24900,0,0],[25200,1,0]],"mustHitSection":true},{"typeOfSection":0,"lengthInSteps":16,"sectionNotes":[[26400,0,0],[26550,1,0],[26850,3,0],[27000,2,0],[27300,3,0],[27450,0,0],[27750,1,0],[28050,0,0],[28200,3,0],[28350,1,0],[28500,2,0]],"mustHitSection":true},{"typeOfSection":0,"lengthInSteps":16,"sectionNotes":[[29748,1,600,0,0,0],[30390,2,900,0,0,0],[28800,5,300],[29400,6,0],[29790,7,0],[30000,4,300],[30300,7,0]],"mustHitSection":false},{"typeOfSection":0,"lengthInSteps":16,"sectionNotes":[[32190,2,0,false,false,null],[33300,3,450,false,false,null],[31282.5,2,0],[32190,0,0],[32400,1,0],[33150,1,150],[32700,0,450],[31500,0,300],[31800,0,300]],"mustHitSection":false},{"typeOfSection":0,"lengthInSteps":16,"sectionNotes":[[33832.5,2,0,false,false,null],[34912.5,1,0,false,false,null],[35250,3,0,false,false,null],[34140,2,0],[34350,2,0],[35100,2,0],[35400,0,0],[35550,3,0],[35700,0,0],[35850,2,0]],"mustHitSection":false},{"typeOfSection":0,"lengthInSteps":16,"sectionNotes":[[36450,0,0,false,false,null],[36600,3,0,false,false,null],[36750,0,0,false,false,null],[36150,5,0],[37050,2,0],[37350,1,0],[37350,5,0],[37650,4,300],[38100,6,0],[38250,7,0]],"mustHitSection":true},{"typeOfSection":0,"lengthInSteps":16,"sectionNotes":[[39300,6,0,false,false,null],[39300,2,0,false,false,null],[38932.5,4,0,false,false,null],[38932.5,3,0,false,false,null],[39900,4,0,false,false,null],[39900,3,0,false,false,null],[39600,4,0],[39600,3,0],[39900,0,0],[39900,7,0],[40200,2,600]],"mustHitSection":true},{"typeOfSection":0,"lengthInSteps":16,"sectionNotes":[[41006.25,2,0],[42000,2,0],[42000,0,0],[42300,1,0],[41250,0,300],[42555,0,300],[42978.75,1,150],[41550,0,450]],"mustHitSection":true},{"typeOfSection":0,"lengthInSteps":16,"sectionNotes":[[44700,1,0,false,false,null],[43200,3,450],[43650,2,0],[43867.5,2,0],[44100,2,0],[44850,2,0],[45000,3,0],[45150,0,0],[45300,3,0]],"mustHitSection":true},{"typeOfSection":0,"lengthInSteps":16,"sectionNotes":[[45600,6,0,false,false,null],[47475,6,0,false,false,null],[47917.5,6,0,false,false,null],[45900,5,0],[46200,0,0],[46350,3,0],[46500,0,0],[46650,3,0],[46800,2,0],[47100,1,0],[47178.75,7,0]],"mustHitSection":false},{"typeOfSection":0,"lengthInSteps":16,"sectionNotes":[[48048.75,4,0,false,false,null],[49050,6,0,false,false,null],[49050,2,0,false,false,null],[49312.5,7,0,false,false,null],[49323.75,0,0,false,false,null],[49650,4,0,false,false,null],[49650,3,0,false,false,null],[50133.75,1,0,false,false,null],[50295,3,0,false,false,null],[49650,7,0],[49650,0,0],[48663.75,7,0],[48671.25,0,0]],"mustHitSection":false},{"typeOfSection":0,"lengthInSteps":16,"sectionNotes":[[50700,1,0,false,false,null],[50883.75,0,0,false,false,null],[51600,0,0,false,false,null],[51690,3,0,false,false,null],[51810,0,0,false,false,null],[52001.25,2,0,false,false,null],[52200,2,0,false,false,null],[52301.25,0,0,false,false,null],[51000,2,0],[51150,3,150],[51450,1,0],[52117.5,3,0],[50400,0,300],[52500,3,0],[52650,1,300]],"mustHitSection":false},{"typeOfSection":0,"lengthInSteps":16,"sectionNotes":[[53250,2,150],[53550,3,150],[53850,0,150],[54450,1,300],[55050,5,0],[54071.25,2,0]],"mustHitSection":false},{"typeOfSection":0,"lengthInSteps":16,"sectionNotes":[[55200,3,0,false,false,null],[55650,1,0,false,false,null],[56718.75,3,0,false,false,null],[56913.75,0,0,false,false,null],[57341.25,3,0,false,false,null],[55800,0,0],[56550,0,0],[57150,2,0],[55950,3,150],[55350,0,300],[57450,1,300]],"mustHitSection":true},{"typeOfSection":0,"lengthInSteps":16,"sectionNotes":[[58421.25,3,0,false,false,null],[59763.75,2,0,false,false,null],[59756.25,6,0,false,false,null],[58050,2,0],[58863.75,0,150],[59400,1,150],[59100,2,0]],"mustHitSection":true},{"typeOfSection":0,"lengthInSteps":16,"sectionNotes":[[60517.5,3,0,false,false,null],[60750,2,0,false,false,null],[61128.75,3,0,false,false,null],[61650,3,0,false,false,null],[61398.75,0,0,false,false,null],[62032.5,3,0,false,false,null],[62325,2,0,false,false,null],[60071.25,5,0,false,false,null],[60517.5,4,0,false,false,null],[60750,6,0,false,false,null],[61132.5,4,0,false,false,null],[61387.5,7,0,false,false,null],[61650,4,0,false,false,null],[62032.5,4,0,false,false,null],[62325,6,0,false,false,null],[60090,2,0],[60300,3,0],[60300,4,0],[61500,5,0],[61500,2,0],[62021.25,7,0],[62036.25,0,0],[62325,3,0],[62325,4,0]],"mustHitSection":false},{"typeOfSection":0,"lengthInSteps":16,"sectionNotes":[[62490,1,300,false,false,null],[63558.75,3,0,false,false,null],[64200,3,0,false,false,null],[64650,2,0,false,false,null],[62478.75,5,300,false,false,null],[63000,4,0,false,false,null],[63566.25,4,0,false,false,null],[64200,4,0,false,false,null],[64650,6,0,false,false,null],[63000,3,0],[63900,2,0],[63900,6,0],[64200,7,0],[64200,0,0]],"mustHitSection":true},{"typeOfSection":0,"lengthInSteps":16,"sectionNotes":[[64800,3,0,false,false,null],[65550,1,0,false,false,null],[66521.25,0,0,false,false,null],[66948.75,2,0,false,false,null],[64800,4,0,false,false,null],[65550,5,0,false,false,null],[66300,4,0,false,false,null],[66300,3,0,false,false,null],[65850,3,0,false,false,null],[65850,4,0,false,false,null],[66510,7,0,false,false,null],[66937.5,6,0,false,false,null],[64950,2,300],[64950,6,300],[65325,5,0],[65328.75,1,0],[65550,0,0],[65550,7,0],[66093.75,7,0],[66105,0,0],[66750,5,0],[66750,1,0]],"mustHitSection":false},{"typeOfSection":0,"lengthInSteps":16,"sectionNotes":[[67200,4,0,false,false,null],[67350,7,0,false,false,null],[67800,4,0,false,false,null],[68137.5,6,0,false,false,null],[68486.25,7,0,false,false,null],[67200,3,0,false,false,null],[67350,0,0,false,false,null],[67800,3,0,false,false,null],[69450,6,750,false,false,null],[69450,2,1650,false,false,null],[67350,4,0],[67350,3,0],[67800,7,0],[67800,0,0],[68156.25,2,0],[68493.75,0,0],[68497.5,4,0],[68497.5,3,0]],"mustHitSection":true},{"typeOfSection":0,"lengthInSteps":16,"sectionNotes":[[70252.5,2,0,false,false,null],[71400,0,0,false,false,null],[71700,3,300,false,false,null],[71250,7,600,false,false,null],[71850,4,1800,false,false,null],[71171.25,3,0],[70567.5,3,300],[70908.75,3,150]],"mustHitSection":false},{"typeOfSection":0,"lengthInSteps":16,"sectionNotes":[[72802.5,3,0,false,false,null],[72150,1,150],[73905,0,0],[74100,2,0],[74250,0,0],[73050,2,0],[73350,1,0],[72450,0,0],[72600,2,150]],"mustHitSection":false},{"typeOfSection":0,"lengthInSteps":16,"sectionNotes":[[76308.75,6,0,false,false,null],[76650,4,0,false,false,null],[74400,7,0],[74550,4,0],[74700,7,0],[74850,5,0],[75150,6,0],[75450,0,0],[75600,3,0],[75750,0,0],[76050,2,0],[76350,1,0],[76650,7,0]],"mustHitSection":true},{"lengthInSteps":16,"sectionNotes":[[77043.75,3,0,false,false,null],[77302.5,0,0,false,false,null],[77940,7,0,false,false,null],[77943.75,0,0,false,false,null],[78300,0,0,false,false,null],[78300,7,0,false,false,null],[79147.5,2,1650,false,false,null],[78570,2,0],[78573.75,6,0],[78851.25,5,0],[78847.5,1,0],[78300,4,0],[78300,3,0],[79128.75,6,900]],"typeOfSection":0,"mustHitSection":false,"changeBPM":false,"bpm":100},{"sectionNotes":[[80913.75,4,600,false,false,null],[80025,2,0,false,false,null],[81000,3,0],[81255,0,0],[81513.75,3,150],[80400,3,300],[80700,3,300]],"typeOfSection":0,"lengthInSteps":16,"altAnim":false,"mustHitSection":true,"changeBPM":false,"bpm":100},{"sectionNotes":[[81637.5,7,2100,false,false,null],[82650,3,0,false,false,null],[82800,2,0,false,false,null],[83100,1,0],[83550,2,0],[83850,0,0],[81750,1,300],[82050,0,150],[82200,2,450]],"typeOfSection":0,"lengthInSteps":16,"altAnim":false,"mustHitSection":true,"changeBPM":false,"bpm":100},{"sectionNotes":[[84000,3,0,false,false,null],[84600,2,0,false,false,null],[85200,7,0,false,false,null],[85800,6,0,false,false,null],[84150,0,0],[84300,3,0],[84900,1,0],[85350,4,0],[85500,7,0],[85650,4,0],[86100,5,0],[86100,2,0]],"typeOfSection":0,"lengthInSteps":16,"altAnim":false,"mustHitSection":true,"changeBPM":false,"bpm":100},{"lengthInSteps":16,"typeOfSection":0,"sectionNotes":[[87045,0,0,false,false,null],[88260,7,0,false,false,null],[86850,0,0],[86400,0,450],[88567.5,5,0],[88571.25,1,0],[88050,2,0],[88050,6,0],[87600,6,450],[87600,2,450],[88267.5,0,0]],"altAnim":false,"bpm":100,"changeBPM":false,"mustHitSection":true},{"lengthInSteps":16,"typeOfSection":0,"sectionNotes":[],"altAnim":false,"bpm":100,"changeBPM":false,"mustHitSection":true},{"lengthInSteps":16,"typeOfSection":0,"sectionNotes":[],"altAnim":false,"bpm":100,"changeBPM":false,"mustHitSection":true},{"sectionNotes":[],"typeOfSection":0,"lengthInSteps":16,"altAnim":false,"mustHitSection":true,"changeBPM":false,"bpm":100},{"lengthInSteps":16,"typeOfSection":0,"sectionNotes":[],"altAnim":false,"bpm":100,"changeBPM":false,"mustHitSection":true},{"lengthInSteps":16,"typeOfSection":0,"sectionNotes":[],"altAnim":false,"bpm":100,"changeBPM":false,"mustHitSection":true},{"sectionNotes":[],"typeOfSection":0,"lengthInSteps":16,"altAnim":false,"mustHitSection":true,"changeBPM":false,"bpm":100},{"sectionNotes":[],"typeOfSection":0,"lengthInSteps":16,"altAnim":false,"mustHitSection":true,"changeBPM":false,"bpm":100},{"sectionNotes":[],"typeOfSection":0,"lengthInSteps":16,"altAnim":false,"mustHitSection":true,"changeBPM":false,"bpm":100},{"sectionNotes":[],"typeOfSection":0,"lengthInSteps":16,"altAnim":false,"mustHitSection":true,"changeBPM":false,"bpm":100},{"sectionNotes":[],"typeOfSection":0,"lengthInSteps":16,"altAnim":false,"mustHitSection":true,"changeBPM":false,"bpm":100},{"sectionNotes":[],"typeOfSection":0,"lengthInSteps":16,"altAnim":false,"mustHitSection":true,"changeBPM":false,"bpm":100},{"sectionNotes":[],"typeOfSection":0,"lengthInSteps":16,"altAnim":false,"mustHitSection":true,"changeBPM":false,"bpm":100},{"lengthInSteps":16,"typeOfSection":0,"sectionNotes":[],"altAnim":false,"bpm":100,"changeBPM":false,"mustHitSection":true},{"sectionNotes":[],"typeOfSection":0,"lengthInSteps":16,"altAnim":false,"mustHitSection":true,"changeBPM":false,"bpm":100},{"lengthInSteps":16,"typeOfSection":0,"sectionNotes":[],"altAnim":false,"bpm":100,"changeBPM":false,"mustHitSection":true},{"sectionNotes":[],"typeOfSection":0,"lengthInSteps":16,"altAnim":false,"mustHitSection":true,"changeBPM":false,"bpm":100},{"lengthInSteps":16,"altAnim":false,"typeOfSection":0,"sectionNotes":[],"bpm":98,"changeBPM":false,"mustHitSection":true}],"sections":54,"bpm":98,"song":{"player1":"bf","sectionLengths":[],"player2":"dad","notes":[{"typeOfSection":0,"lengthInSteps":16,"sectionNotes":[],"mustHitSection":true},{"typeOfSection":0,"lengthInSteps":16,"sectionNotes":[],"mustHitSection":true},{"typeOfSection":0,"lengthInSteps":16,"sectionNotes":[],"mustHitSection":false},{"typeOfSection":0,"lengthInSteps":16,"sectionNotes":[],"mustHitSection":false},{"typeOfSection":0,"lengthInSteps":16,"sectionNotes":[[11002.5,6,0,false,false,null],[11737.5,7,0,false,false,null],[11925,4,450,false,false,null],[10305,2,0,false,false,null],[10590,1,0,false,false,null],[9960,3,0,false,false,null],[10098.75,0,0,false,false,null],[9791.25,3,0],[9633.75,3,0],[10350,3,0],[10650,0,0],[11512.5,5,150],[11100,7,300]],"mustHitSection":true},{"typeOfSection":0,"lengthInSteps":16,"sectionNotes":[[12390,1,0,false,false,null],[12813.75,3,0,false,false,null],[13275,2,0,false,false,null],[13571.25,0,0,false,false,null],[14250,3,0,false,false,null],[13050,3,0],[13278.75,3,0],[13800,2,150],[14250,0,0],[12945,0,0],[12671.25,0,0]],"mustHitSection":false},{"typeOfSection":0,"lengthInSteps":16,"sectionNotes":[[15881.25,2,0,false,false,null],[16350,3,0,false,false,null],[16616.25,0,0,false,false,null],[14763.75,1,0],[15108.75,2,0],[15450,3,0],[14756.25,3,0],[15108.75,0,0],[15450,1,0],[16200,0,0]],"mustHitSection":false},{"typeOfSection":0,"lengthInSteps":16,"sectionNotes":[[16800,1,0,false,false,null],[17062.5,3,0,false,false,null],[17287.5,2,0,false,false,null],[17550,3,0,false,false,null],[17745,0,0,false,false,null],[19136.25,1,450,false,false,null],[17940,1,0],[18663.75,2,0],[18150,0,450]],"mustHitSection":false},{"typeOfSection":0,"lengthInSteps":16,"sectionNotes":[[19751.25,2,0,false,false,null],[20013.75,3,0,false,false,null],[20801.25,6,0,false,false,null],[20895,7,0],[21093.75,4,0],[21300,5,150],[21525,7,0],[20250,0,300],[20550,3,0]],"mustHitSection":false},{"typeOfSection":0,"lengthInSteps":16,"sectionNotes":[[22117.5,1,0],[22350,0,0],[22586.25,3,0],[22725,0,0],[23021.25,3,0],[23017.5,2,0],[23400,0,0],[23550,2,150],[21675,0,300]],"mustHitSection":true},{"typeOfSection":0,"lengthInSteps":16,"sectionNotes":[[24000,0,0],[24000,3,0],[24600,1,0],[24900,2,0],[25200,3,0],[25650,2,0],[25950,2,0],[26100,3,0],[24600,3,0],[24900,0,0],[25200,1,0]],"mustHitSection":true},{"typeOfSection":0,"lengthInSteps":16,"sectionNotes":[[26400,0,0],[26550,1,0],[26850,3,0],[27000,2,0],[27300,3,0],[27450,0,0],[27750,1,0],[28050,0,0],[28200,3,0],[28350,1,0],[28500,2,0]],"mustHitSection":true},{"typeOfSection":0,"lengthInSteps":16,"sectionNotes":[[29748,1,600,0,0,0],[30390,2,900,0,0,0],[28800,5,300],[29400,6,0],[29790,7,0],[30000,4,300],[30300,7,0]],"mustHitSection":false},{"typeOfSection":0,"lengthInSteps":16,"sectionNotes":[[32190,2,0,false,false,null],[33300,3,450,false,false,null],[31282.5,2,0],[32190,0,0],[32400,1,0],[33150,1,150],[32700,0,450],[31500,0,300],[31800,0,300]],"mustHitSection":false},{"typeOfSection":0,"lengthInSteps":16,"sectionNotes":[[33832.5,2,0,false,false,null],[34912.5,1,0,false,false,null],[35250,3,0,false,false,null],[34140,2,0],[34350,2,0],[35100,2,0],[35400,0,0],[35550,3,0],[35700,0,0],[35850,2,0]],"mustHitSection":false},{"typeOfSection":0,"lengthInSteps":16,"sectionNotes":[[36450,0,0,false,false,null],[36600,3,0,false,false,null],[36750,0,0,false,false,null],[36150,5,0],[37050,2,0],[37350,1,0],[37350,5,0],[37650,4,300],[38100,6,0],[38250,7,0]],"mustHitSection":true},{"typeOfSection":0,"lengthInSteps":16,"sectionNotes":[[39300,6,0,false,false,null],[39300,2,0,false,false,null],[38932.5,4,0,false,false,null],[38932.5,3,0,false,false,null],[39900,4,0,false,false,null],[39900,3,0,false,false,null],[39600,4,0],[39600,3,0],[39900,0,0],[39900,7,0],[40200,2,600]],"mustHitSection":true},{"typeOfSection":0,"lengthInSteps":16,"sectionNotes":[[41006.25,2,0],[42000,2,0],[42000,0,0],[42300,1,0],[41250,0,300],[42555,0,300],[42978.75,1,150],[41550,0,450]],"mustHitSection":true},{"typeOfSection":0,"lengthInSteps":16,"sectionNotes":[[44700,1,0,false,false,null],[43200,3,450],[43650,2,0],[43867.5,2,0],[44100,2,0],[44850,2,0],[45000,3,0],[45150,0,0],[45300,3,0]],"mustHitSection":true},{"typeOfSection":0,"lengthInSteps":16,"sectionNotes":[[45600,6,0,false,false,null],[47475,6,0,false,false,null],[47917.5,6,0,false,false,null],[45900,5,0],[46200,0,0],[46350,3,0],[46500,0,0],[46650,3,0],[46800,2,0],[47100,1,0],[47178.75,7,0]],"mustHitSection":false},{"typeOfSection":0,"lengthInSteps":16,"sectionNotes":[[48048.75,4,0,false,false,null],[49050,6,0,false,false,null],[49050,2,0,false,false,null],[49312.5,7,0,false,false,null],[49323.75,0,0,false,false,null],[49650,4,0,false,false,null],[49650,3,0,false,false,null],[50133.75,1,0,false,false,null],[50295,3,0,false,false,null],[49650,7,0],[49650,0,0],[48663.75,7,0],[48671.25,0,0]],"mustHitSection":false},{"typeOfSection":0,"lengthInSteps":16,"sectionNotes":[[50700,1,0,false,false,null],[50883.75,0,0,false,false,null],[51600,0,0,false,false,null],[51690,3,0,false,false,null],[51810,0,0,false,false,null],[52001.25,2,0,false,false,null],[52200,2,0,false,false,null],[52301.25,0,0,false,false,null],[51000,2,0],[51150,3,150],[51450,1,0],[52117.5,3,0],[50400,0,300],[52500,3,0],[52650,1,300]],"mustHitSection":false},{"typeOfSection":0,"lengthInSteps":16,"sectionNotes":[[53250,2,150],[53550,3,150],[53850,0,150],[54450,1,300],[55050,5,0],[54071.25,2,0]],"mustHitSection":false},{"typeOfSection":0,"lengthInSteps":16,"sectionNotes":[[55200,3,0,false,false,null],[55650,1,0,false,false,null],[56718.75,3,0,false,false,null],[56913.75,0,0,false,false,null],[57341.25,3,0,false,false,null],[55800,0,0],[56550,0,0],[57150,2,0],[55950,3,150],[55350,0,300],[57450,1,300]],"mustHitSection":true},{"typeOfSection":0,"lengthInSteps":16,"sectionNotes":[[58421.25,3,0,false,false,null],[59763.75,2,0,false,false,null],[59756.25,6,0,false,false,null],[58050,2,0],[58863.75,0,150],[59400,1,150],[59100,2,0]],"mustHitSection":true},{"typeOfSection":0,"lengthInSteps":16,"sectionNotes":[[60517.5,3,0,false,false,null],[60750,2,0,false,false,null],[61128.75,3,0,false,false,null],[61650,3,0,false,false,null],[61398.75,0,0,false,false,null],[62032.5,3,0,false,false,null],[62325,2,0,false,false,null],[60071.25,5,0,false,false,null],[60517.5,4,0,false,false,null],[60750,6,0,false,false,null],[61132.5,4,0,false,false,null],[61387.5,7,0,false,false,null],[61650,4,0,false,false,null],[62032.5,4,0,false,false,null],[62325,6,0,false,false,null],[60090,2,0],[60300,3,0],[60300,4,0],[61500,5,0],[61500,2,0],[62021.25,7,0],[62036.25,0,0],[62325,3,0],[62325,4,0]],"mustHitSection":false},{"typeOfSection":0,"lengthInSteps":16,"sectionNotes":[[62490,1,300,false,false,null],[63558.75,3,0,false,false,null],[64200,3,0,false,false,null],[64650,2,0,false,false,null],[62478.75,5,300,false,false,null],[63000,4,0,false,false,null],[63566.25,4,0,false,false,null],[64200,4,0,false,false,null],[64650,6,0,false,false,null],[63000,3,0],[63900,2,0],[63900,6,0],[64200,7,0],[64200,0,0]],"mustHitSection":true},{"typeOfSection":0,"lengthInSteps":16,"sectionNotes":[[64800,3,0,false,false,null],[65550,1,0,false,false,null],[66521.25,0,0,false,false,null],[66948.75,2,0,false,false,null],[64800,4,0,false,false,null],[65550,5,0,false,false,null],[66300,4,0,false,false,null],[66300,3,0,false,false,null],[65850,3,0,false,false,null],[65850,4,0,false,false,null],[66510,7,0,false,false,null],[66937.5,6,0,false,false,null],[64950,2,300],[64950,6,300],[65325,5,0],[65328.75,1,0],[65550,0,0],[65550,7,0],[66093.75,7,0],[66105,0,0],[66750,5,0],[66750,1,0]],"mustHitSection":false},{"typeOfSection":0,"lengthInSteps":16,"sectionNotes":[[67200,4,0,false,false,null],[67350,7,0,false,false,null],[67800,4,0,false,false,null],[68137.5,6,0,false,false,null],[68486.25,7,0,false,false,null],[67200,3,0,false,false,null],[67350,0,0,false,false,null],[67800,3,0,false,false,null],[69450,6,750,false,false,null],[69450,2,1650,false,false,null],[67350,4,0],[67350,3,0],[67800,7,0],[67800,0,0],[68156.25,2,0],[68493.75,0,0],[68497.5,4,0],[68497.5,3,0]],"mustHitSection":true},{"typeOfSection":0,"lengthInSteps":16,"sectionNotes":[[70252.5,2,0,false,false,null],[71400,0,0,false,false,null],[71700,3,300,false,false,null],[71250,7,600,false,false,null],[71850,4,1800,false,false,null],[71171.25,3,0],[70567.5,3,300],[70908.75,3,150]],"mustHitSection":false},{"typeOfSection":0,"lengthInSteps":16,"sectionNotes":[[72802.5,3,0,false,false,null],[72150,1,150],[73905,0,0],[74100,2,0],[74250,0,0],[73050,2,0],[73350,1,0],[72450,0,0],[72600,2,150]],"mustHitSection":false},{"typeOfSection":0,"lengthInSteps":16,"sectionNotes":[[76308.75,6,0,false,false,null],[76650,4,0,false,false,null],[74400,7,0],[74550,4,0],[74700,7,0],[74850,5,0],[75150,6,0],[75450,0,0],[75600,3,0],[75750,0,0],[76050,2,0],[76350,1,0],[76650,7,0]],"mustHitSection":true},{"lengthInSteps":16,"sectionNotes":[[77043.75,3,0,false,false,null],[77302.5,0,0,false,false,null],[77940,7,0,false,false,null],[77943.75,0,0,false,false,null],[78300,0,0,false,false,null],[78300,7,0,false,false,null],[79147.5,2,1650,false,false,null],[78570,2,0],[78573.75,6,0],[78851.25,5,0],[78847.5,1,0],[78300,4,0],[78300,3,0],[79128.75,6,900]],"typeOfSection":0,"mustHitSection":false,"changeBPM":false,"bpm":100},{"sectionNotes":[[80913.75,4,600,false,false,null],[80025,2,0,false,false,null],[81000,3,0],[81255,0,0],[81513.75,3,150],[80400,3,300],[80700,3,300]],"typeOfSection":0,"lengthInSteps":16,"altAnim":false,"mustHitSection":true,"changeBPM":false,"bpm":100},{"sectionNotes":[[81637.5,7,2100,false,false,null],[82650,3,0,false,false,null],[82800,2,0,false,false,null],[83100,1,0],[83550,2,0],[83850,0,0],[81750,1,300],[82050,0,150],[82200,2,450]],"typeOfSection":0,"lengthInSteps":16,"altAnim":false,"mustHitSection":true,"changeBPM":false,"bpm":100},{"sectionNotes":[[84000,3,0,false,false,null],[84600,2,0,false,false,null],[85200,7,0,false,false,null],[85800,6,0,false,false,null],[84150,0,0],[84300,3,0],[84900,1,0],[85350,4,0],[85500,7,0],[85650,4,0],[86100,5,0],[86100,2,0]],"typeOfSection":0,"lengthInSteps":16,"altAnim":false,"mustHitSection":true,"changeBPM":false,"bpm":100},{"lengthInSteps":16,"typeOfSection":0,"sectionNotes":[[87045,0,0,false,false,null],[88260,7,0,false,false,null],[86850,0,0],[86400,0,450],[88567.5,5,0],[88571.25,1,0],[88050,2,0],[88050,6,0],[87600,6,450],[87600,2,450],[88267.5,0,0]],"altAnim":false,"bpm":100,"changeBPM":false,"mustHitSection":true},{"lengthInSteps":16,"typeOfSection":0,"sectionNotes":[],"altAnim":false,"bpm":100,"changeBPM":false,"mustHitSection":true},{"lengthInSteps":16,"typeOfSection":0,"sectionNotes":[],"altAnim":false,"bpm":100,"changeBPM":false,"mustHitSection":true},{"sectionNotes":[],"typeOfSection":0,"lengthInSteps":16,"altAnim":false,"mustHitSection":true,"changeBPM":false,"bpm":100},{"lengthInSteps":16,"typeOfSection":0,"sectionNotes":[],"altAnim":false,"bpm":100,"changeBPM":false,"mustHitSection":true},{"lengthInSteps":16,"typeOfSection":0,"sectionNotes":[],"altAnim":false,"bpm":100,"changeBPM":false,"mustHitSection":true},{"sectionNotes":[],"typeOfSection":0,"lengthInSteps":16,"altAnim":false,"mustHitSection":true,"changeBPM":false,"bpm":100},{"sectionNotes":[],"typeOfSection":0,"lengthInSteps":16,"altAnim":false,"mustHitSection":true,"changeBPM":false,"bpm":100},{"sectionNotes":[],"typeOfSection":0,"lengthInSteps":16,"altAnim":false,"mustHitSection":true,"changeBPM":false,"bpm":100},{"sectionNotes":[],"typeOfSection":0,"lengthInSteps":16,"altAnim":false,"mustHitSection":true,"changeBPM":false,"bpm":100},{"sectionNotes":[],"typeOfSection":0,"lengthInSteps":16,"altAnim":false,"mustHitSection":true,"changeBPM":false,"bpm":100},{"sectionNotes":[],"typeOfSection":0,"lengthInSteps":16,"altAnim":false,"mustHitSection":true,"changeBPM":false,"bpm":100},{"sectionNotes":[],"typeOfSection":0,"lengthInSteps":16,"altAnim":false,"mustHitSection":true,"changeBPM":false,"bpm":100},{"lengthInSteps":16,"typeOfSection":0,"sectionNotes":[],"altAnim":false,"bpm":100,"changeBPM":false,"mustHitSection":true},{"sectionNotes":[],"typeOfSection":0,"lengthInSteps":16,"altAnim":false,"mustHitSection":true,"changeBPM":false,"bpm":100},{"lengthInSteps":16,"typeOfSection":0,"sectionNotes":[],"altAnim":false,"bpm":100,"changeBPM":false,"mustHitSection":true},{"sectionNotes":[],"typeOfSection":0,"lengthInSteps":16,"altAnim":false,"mustHitSection":true,"changeBPM":false,"bpm":100},{"lengthInSteps":16,"altAnim":false,"typeOfSection":0,"sectionNotes":[],"bpm":98,"changeBPM":false,"mustHitSection":true}],"song":"Bopeebo","validScore":true,"sections":0,"needsVoices":true,"bpm":98,"speed":1.6}}