<?xml version="1.0" encoding="utf-8"?>
<TextureAtlas imagePath="SCgfassetscar.png">
	<!-- Created with Adobe Animate version 21.0.4.39603 -->
	<!-- http://www.adobe.com/products/animate.html -->
	<SubTexture name="GF Dancing Beat Hair blowing CAR0000" x="0" y="0" width="776" height="691"/>
	<SubTexture name="GF Dancing Beat Hair blowing CAR0001" x="776" y="0" width="776" height="691"/>
	<SubTexture name="GF Dancing Beat Hair blowing CAR0002" x="1552" y="0" width="776" height="691"/>
	<SubTexture name="GF Dancing Beat Hair blowing CAR0003" x="2328" y="0" width="776" height="691"/>
	<SubTexture name="GF Dancing Beat Hair blowing CAR0004" x="3104" y="0" width="776" height="691"/>
	<SubTexture name="GF Dancing Beat Hair blowing CAR0005" x="3880" y="0" width="776" height="691"/>
	<SubTexture name="GF Dancing Beat Hair blowing CAR0006" x="4656" y="0" width="776" height="691"/>
	<SubTexture name="GF Dancing Beat Hair blowing CAR0007" x="5432" y="0" width="776" height="691"/>
	<SubTexture name="GF Dancing Beat Hair blowing CAR0008" x="6208" y="0" width="776" height="691"/>
	<SubTexture name="GF Dancing Beat Hair blowing CAR0009" x="6984" y="0" width="776" height="691"/>
	<SubTexture name="GF Dancing Beat Hair blowing CAR0010" x="0" y="691" width="776" height="691"/>
	<SubTexture name="GF Dancing Beat Hair blowing CAR0011" x="0" y="691" width="776" height="691"/>
	<SubTexture name="GF Dancing Beat Hair blowing CAR0012" x="776" y="691" width="776" height="691"/>
	<SubTexture name="GF Dancing Beat Hair blowing CAR0013" x="1552" y="691" width="776" height="691"/>
	<SubTexture name="GF Dancing Beat Hair blowing CAR0014" x="2328" y="691" width="776" height="691"/>
	<SubTexture name="GF Dancing Beat Hair blowing CAR0015" x="3104" y="691" width="776" height="691"/>
	<SubTexture name="GF Dancing Beat Hair blowing CAR0016" x="3880" y="691" width="776" height="691"/>
	<SubTexture name="GF Dancing Beat Hair blowing CAR0017" x="4656" y="691" width="776" height="691"/>
	<SubTexture name="GF Dancing Beat Hair blowing CAR0018" x="5432" y="691" width="776" height="691"/>
	<SubTexture name="GF Dancing Beat Hair blowing CAR0019" x="6208" y="691" width="776" height="691"/>
	<SubTexture name="GF Dancing Beat Hair blowing CAR0020" x="6984" y="691" width="776" height="691"/>
	<SubTexture name="GF Dancing Beat Hair blowing CAR0021" x="0" y="1382" width="776" height="691"/>
	<SubTexture name="GF Dancing Beat Hair blowing CAR0022" x="776" y="1382" width="776" height="691"/>
	<SubTexture name="GF Dancing Beat Hair blowing CAR0023" x="1552" y="1382" width="776" height="691"/>
	<SubTexture name="GF Dancing Beat Hair blowing CAR0024" x="2328" y="1382" width="776" height="691"/>
	<SubTexture name="GF Dancing Beat Hair blowing CAR0025" x="3104" y="1382" width="776" height="691"/>
	<SubTexture name="GF Dancing Beat Hair blowing CAR0026" x="3880" y="1382" width="776" height="691"/>
	<SubTexture name="GF Dancing Beat Hair blowing CAR0027" x="4656" y="1382" width="776" height="691"/>
	<SubTexture name="GF Dancing Beat Hair blowing CAR0028" x="5432" y="1382" width="776" height="691"/>
	<SubTexture name="GF Dancing Beat Hair blowing CAR0029" x="6208" y="1382" width="776" height="691"/>
</TextureAtlas>
